{
  "project_info": {
    "project_number": "847872203451",
    "project_id": "rural4us",
    "storage_bucket": "rural4us.appspot.com"
  },
  "client": [
    {
      "client_info": {
        "mobilesdk_app_id": "1:847872203451:android:68f68cc583860ec58f279e",
        "android_client_info": {
          "package_name": "com.example.flutter_catalog"
        }
      },
      "oauth_client": [
        {
          "client_id": "847872203451-4mp02rjcq720upl1jlpau7spppf3bek4.apps.googleusercontent.com",
          "client_type": 3
        }
      ],
      "api_key": [
        {
          "current_key": "AIzaSyD8aWDPuEuL2b1LKFmLrLf1LdAwdAZkWIA"
        }
      ],
      "services": {
        "appinvite_service": {
          "other_platform_oauth_client": [
            {
              "client_id": "847872203451-4mp02rjcq720upl1jlpau7spppf3bek4.apps.googleusercontent.com",
              "client_type": 3
            }
          ]
        }
      }
    }
  ],
  "configuration_version": "1"
}